rwthomework/__init__.py
rwthomework/moodle/__init__.py
rwthomework/textools/__init__.py
rwthomework-0.0.3.3.dist-info/licenses/LICENSE
rwthomework-0.0.3.3.dist-info/METADATA
rwthomework-0.0.3.3.dist-info/WHEEL
rwthomework-0.0.3.3.dist-info/top_level.txt
rwthomework-0.0.3.3.dist-info/RECORD
