Metadata-Version: 2.4
Name: rwthomework
Version: 0.0.3.3
Summary: A package for utility functions for physics homework
Author-email: Manuel Biwer <manuel.biwer@rwth-aachen.de>, Janik Heiler <janik.heiler@rwth-aachen.de>
License-Expression: GPL-3.0
Project-URL: Homepage, https://github.com/Nimrenyi/rwthomework
Project-URL: Issues, https://github.com/Nimrenyi/rwthomework/issues
Classifier: Programming Language :: Python :: 3
Classifier: Operating System :: OS Independent
Requires-Python: >=3.10
License-File: LICENSE
Requires-Dist: matplotlib
Requires-Dist: requests
Dynamic: license-file
